{
  "users": [
    {
      "id": 1,
      "name": "User",
      "lastname": "One",
      "email": "userOne@mail.com",
      "username": "user-one",
      "password": "password"
    },
    {
      "id": 2,
      "name": "User",
      "lastname": "Two",
      "email": "userTwo@mail.com",
      "username": "user-two",
      "password": "password"
    },
    {
      "id": 3,
      "name": "User",
      "lastname": "Three",
      "email": "userThree@mail.com",
      "username": "user-three",
      "password": "password"
    },
    {
      "id": 4,
      "name": "User",
      "lastname": "Four",
      "email": "userFour@mail.com",
      "username": "user-four",
      "password": "password"
    },
    {
      "name": "User",
      "lastname": "Five",
      "email": "userFive@mail.com",
      "username": "user-five",
      "password": "password",
      "id": 5
    }
  ],
  "items": [
    {
      "id": 1,
      "name": "Item MODIFI",
      "description": "This is item One",
      "value": "3",
      "Description": "This is item One"
    },
    {
      "id": 2,
      "name": "Item 1",
      "description": "This is item Two",
      "value": 2
    },
    {
      "id": 3,
      "name": "Item 1",
      "description": "This is item Three",
      "value": 3
    }
  ],
  "plantas": [
    {
      "id": 1,
      "name": "Ficus",
      "description": "Planta de sombra ideal para interiores. Compra protegida",
      "costo": "45",
      "imagen": "../Gallery/Planta2.jpg",
      "quantity": ""
    },
    {
      "id": 2,
      "name": "Oregano",
      "description": "Planta de sombra ideal para interiores. Compra protegida",
      "costo": "50",
      "imagen": "../Gallery/Planta3.jpg",
      "quantity": ""
    },
    {
      "id": 3,
      "name": "Pata de elefante",
      "description": "Planta de sombra ideal para interiores. Compra protegida",
      "costo": "120",
      "imagen": "../Gallery/Planta1.jpg",
      "quantity": ""
    },
    {
      "id": 4,
      "name": "Planta de espinaca",
      "description": "Planta de sombra ideal para interiores. Compra protegida",
      "costo": "34",
      "imagen": "../Gallery/Planta4.jpg",
      "quantity": ""
    },
    {
      "id": 5,
      "name": "Planta de tomate",
      "description": "Planta de sombra ideal para interiores. Compra protegida",
      "costo": "40",
      "imagen": "../Gallery/Planta5.jpg",
      "quantity": ""
    },
    {
      "id": 6,
      "name": "Planta de flores",
      "description": "Planta de sombra ideal para interiores. Compra protegida",
      "costo": "90",
      "imagen": "../Gallery/Planta6.jpg",
      "quantity": ""
    }
  ],
  "mesas": [
    {
      "id": 101,
      "name": "Mesa de cultivo RSF789",
      "description": "Mesa de cultivo con patas, madera de pino. Compra protegida",
      "costo": "562",
      "imagen": "../Gallery/Mesa1.jpg",
      "quantity": ""
    },
    {
      "id": 102,
      "name": "Mesa de cultivo RSH345",
      "description": "Mesa de cultivo metálica con patas. Compra protegida",
      "costo": "845",
      "imagen": "../Gallery/Mesa2.jpg",
      "quantity": ""
    },
    {
      "id": 103,
      "name": "Mesa de cultivo RHSJ678",
      "description": "Mesa de cultivo con patas.Material: madera de pino. Compra protegida",
      "costo": "1256",
      "imagen": "../Gallery/Mesa3.jpg",
      "quantity": ""
    },
    {
      "id": 104,
      "name": "Mesa de cultivo FHDJK789",
      "description": "Mesa de cultivo tipo invernadero. Materiales: pino, plástico. Compra protegida",
      "costo": "1300",
      "imagen": "../Gallery/Mesa4.jpg",
      "quantity": ""
    },
    {
      "id": 105,
      "name": "Mesa de cultivo SKJDY0354",
      "description": "Mesa de cultivo metálica.Compatimento inferior. Compra protegida",
      "costo": "862",
      "imagen": "../Gallery/Mesa5.jpg",
      "quantity": ""
    },
    {
      "id": 106,
      "name": "Mesa de cultivo HDJK2738",
      "description": "Mesa de cultivo sin patas.Material: madera. Compra protegida",
      "costo": "1561",
      "imagen": "../Gallery/Mesa6.jpg",
      "quantity": ""
    }
  ],
  "herramientas": [
    {
      "id": 201,
      "name": "Herramientas M7874GH",
      "description": "Kit de herramientas, idel para tu huerto urbano. Compra protegida",
      "costo": "200",
      "imagen": "../Gallery/Her1.jpg",
      "quantity": ""
    },
    {
      "id": 202,
      "name": "Herramientas HHK789",
      "description": "Kit de herramientas, idel para tu huerto urbano. Compra protegida",
      "costo": "160",
      "imagen": "../Gallery/Her2.jpg",
      "quantity": ""
    },
    {
      "id": 203,
      "name": "Herramientas NMVCG345",
      "description": "Kit de herramientas, idel para tu huerto urbano. Compra protegida",
      "costo": "123",
      "imagen": "../Gallery/Her3.jpg",
      "quantity": ""
    },
    {
      "id": 204,
      "name": "Herramientas HJL3489",
      "description": "Kit de herramientas, idel para tu huerto urbano. Compra protegida",
      "costo": "256",
      "imagen": "../Gallery/Her4.jpg",
      "quantity": ""
    },
    {
      "id": 205,
      "name": "Herramientas NMH678",
      "description": "Kit de herramientas, idel para tu huerto urbano. Compra protegida",
      "costo": "134",
      "imagen": "../Gallery/Her5.jpg",
      "quantity": ""
    },
    {
      "id": 206,
      "name": "Herramientas NMJH4678",
      "description": "Kit de herramientas, idel para tu huerto urbano. Compra protegida",
      "costo": "234",
      "imagen": "../Gallery/Her6.jpg",
      "quantity": ""
    }
  ],
  "kits": [
    {
      "id": 301,
      "name": "Kit Huerto Urbano BNMH45567",
      "description": "Ideal para comenzar tu huerto. Compra protegida",
      "costo": "500",
      "imagen": "../Gallery/Kit1.jpg",
      "quantity": ""
    },
    {
      "id": 302,
      "name": "Kit Huerto Urbano BNKH7854",
      "description": "Ideal para comenzar tu huerto. Compra protegida",
      "costo": "345",
      "imagen": "../Gallery/Kit2.jpg",
      "quantity": ""
    },
    {
      "id": 303,
      "name": "Kit Huerto Urbano BJHG567",
      "description": "Ideal para comenzar tu huerto. Compra protegida",
      "costo": "400",
      "imagen": "../Gallery/Kit3.jpg",
      "quantity": ""
    },
    {
      "id": 304,
      "name": "Kit Huerto Urbano NBV345",
      "description": "Ideal para comenzar tu huerto. Compra protegida",
      "costo": "432",
      "imagen": "../Gallery/Kit4.jpg",
      "quantity": ""
    },
    {
      "id": 305,
      "name": "Kit Huerto Urbano BNM467",
      "description": "Ideal para comenzar tu huerto. Compra protegida",
      "costo": "567",
      "imagen": "../Gallery/Kit5.jpg",
      "quantity": ""
    },
    {
      "id": 306,
      "name": "Kit Huerto Urbano BNM789",
      "description": "Ideal para comenzar tu huerto. Compra protegida",
      "costo": "456",
      "imagen": "../Gallery/Kit6.jpg",
      "quantity": ""
    }
  ],
  "macetas": [
    {
      "id": 401,
      "name": "Maceta MOD890",
      "description": "Kit de 10 macetas de barro. Compra protegida",
      "costo": "56",
      "imagen": "../Gallery/Maceta1.jpg",
      "quantity": ""
    },
    {
      "id": 402,
      "name": "Maceta MOD894",
      "description": "Kit 5 Macetas geométricas de cemento. Compra protegida",
      "costo": "500",
      "imagen": "../Gallery/Maceta2.jpg",
      "quantity": ""
    },
    {
      "id": 403,
      "name": "Maceta MOD896",
      "description": "Maceta grande tipo huacal. Compra protegida",
      "costo": "300",
      "imagen": "../Gallery/Maceta3.jpg",
      "quantity": ""
    },
    {
      "id": 404,
      "name": "Maceta MOD899",
      "description": "Maceta tipo cajón de madera. Compra protegida",
      "costo": "345",
      "imagen": "../Gallery/Maceta4.jpg",
      "quantity": ""
    },
    {
      "id": 405,
      "name": "Maceta MOD845",
      "description": "Kit de 3 macetas de barror. Compra protegida",
      "costo": "200",
      "imagen": "../Gallery/Maceta5.jpg",
      "quantity": ""
    },
    {
      "id": 406,
      "name": "Maceta MOD845",
      "description": "Maceta de madera con patas. Compra protegida",
      "costo": "350",
      "imagen": "../Gallery/Maceta6.jpg",
      "quantity": ""
    }
  ],
  "semillas": [
    {
      "id": 501,
      "name": "Semillas RSF789",
      "description": "Kit de 5 tipos de semillas. Compra protegida",
      "costo": "50",
      "imagen": "../Gallery/Semillas1.jpg",
      "quantity": ""
    },
    {
      "id": 502,
      "name": "Semillas RSH345",
      "description": "Kit de 10 sobres. Compra protegida",
      "costo": "72",
      "imagen": "../Gallery/Semillas2.jpg",
      "quantity": ""
    },
    {
      "id": 503,
      "name": "Semillas RHSJ678",
      "description": "Semillas de albhaca. Compra protegida",
      "costo": "30",
      "imagen": "../Gallery/Semillas3.jpg",
      "quantity": ""
    },
    {
      "id": 504,
      "name": "Semillas FHDJK789",
      "description": "Kit de 3 tipos de semillas. Compra protegida",
      "costo": "90",
      "imagen": "../Gallery/Semillas4.jpg",
      "quantity": ""
    },
    {
      "id": 505,
      "name": "Semillas SKJDY0354",
      "description": "Semillas de cactus. Compra protegida",
      "costo": "150",
      "imagen": "../Gallery/Semillas5.jpg",
      "quantity": ""
    },
    {
      "id": 506,
      "name": "Semillas HDJK2738",
      "description": "Semillas de rábano. Compra protegida",
      "costo": "25",
      "imagen": "../Gallery/Semillas6.jpg",
      "quantity": ""
    }
  ],
  "terrarios": [
    {
      "id": 601,
      "name": "Terrario BNH367",
      "description": "Terrario Florilandia de suculentas. Compra protegida",
      "costo": "500",
      "imagen": "../Gallery/Terrario1.jpg",
      "quantity": ""
    },
    {
      "id": 602,
      "name": "Terrario NMBb678",
      "description": "Terrario contenedor alto. Compra protegida",
      "costo": "300",
      "imagen": "../Gallery/Terrario2.jpg",
      "quantity": ""
    },
    {
      "id": 603,
      "name": "Terrario GFD567",
      "description": "Terrario contendor cilíndrico. Compra protegida",
      "costo": "230",
      "imagen": "../Gallery/Terrario3.jpg",
      "quantity": ""
    },
    {
      "id": 604,
      "name": "Terrario HJK345",
      "description": "Juego 2 terrarios geométricos. Compra protegida",
      "costo": "365",
      "imagen": "../Gallery/Terrario4.jpg",
      "quantity": ""
    },
    {
      "id": 605,
      "name": "Terrario JKL789",
      "description": "Terrario sobre corteza de madera. Compra protegida",
      "costo": "356",
      "imagen": "../Gallery/Terrario5.jpg",
      "quantity": ""
    },
    {
      "id": 606,
      "name": "Terrario HJK3789",
      "description": "Terrario Maceta cemento. Compra protegida",
      "costo": "256",
      "imagen": "../Gallery/Terrario6.jpg",
      "quantity": ""
    }
  ],
  "arreglos": [
    {
      "id": 701,
      "name": "Arreglo BNH367",
      "description": "Bonita maceta con planta. Set 2 macetas. Compra protegida",
      "costo": "300",
      "imagen": "../Gallery/Arreglo1.jpg",
      "quantity": ""
    },
    {
      "id": 702,
      "name": "Arreglo NMBb678",
      "description": "Bonita maceta con planta. Set 5 macetas. Compra protegida",
      "costo": "500",
      "imagen": "../Gallery/Arreglo2.jpg",
      "quantity": ""
    },
    {
      "id": 703,
      "name": "Arreglo GFD567",
      "description": "Bonita maceta con planta. Set 3 macetas. Compra protegida",
      "costo": "300",
      "imagen": "../Gallery/Arreglo3.jpg",
      "quantity": ""
    },
    {
      "id": 704,
      "name": "Arreglo HJK345",
      "description": "Bonita maceta con planta. Compra protegida",
      "costo": "150",
      "imagen": "../Gallery/Arreglo4.jpg",
      "quantity": ""
    },
    {
      "id": 705,
      "name": "Arreglo JKL789",
      "description": "Bonita maceta con planta. Set 2 macetas. Compra protegida",
      "costo": "300",
      "imagen": "../Gallery/Arreglo5.jpg",
      "quantity": ""
    },
    {
      "id": 706,
      "name": "Arreglo HJK3789",
      "description": "Bonita maceta con planta. Set 3 macetas. Compra protegida",
      "costo": "500",
      "imagen": "../Gallery/Arreglo6.jpg",
      "quantity": ""
    }
  ],
  "carrito": [
    {
      "id": 1,
      "name": "Ficus",
      "description": "Planta de sombra ideal para interiores. Compra protegida",
      "costo": "45",
      "imagen": "../Gallery/Planta2.jpg",
      "quantity": 2
    },
    {
      "id": 4,
      "name": "Planta de espinaca",
      "description": "Planta de sombra ideal para interiores. Compra protegida",
      "costo": "34",
      "imagen": "../Gallery/Planta4.jpg",
      "quantity": 1
    },
    {
      "id": 105,
      "name": "Mesa de cultivo SKJDY0354",
      "description": "Mesa de cultivo metálica.Compatimento inferior. Compra protegida",
      "costo": "862",
      "imagen": "../Gallery/Mesa5.jpg",
      "quantity": 1
    },
    {
      "id": 106,
      "name": "Mesa de cultivo HDJK2738",
      "description": "Mesa de cultivo sin patas.Material: madera. Compra protegida",
      "costo": "1561",
      "imagen": "../Gallery/Mesa6.jpg",
      "quantity": 1
    },
    {
      "id": 505,
      "name": "Semillas SKJDY0354",
      "description": "Semillas de cactus. Compra protegida",
      "costo": "150",
      "imagen": "../Gallery/Semillas5.jpg",
      "quantity": 1
    },
    {
      "id": 503,
      "name": "Semillas RHSJ678",
      "description": "Semillas de albhaca. Compra protegida",
      "costo": "30",
      "imagen": "../Gallery/Semillas3.jpg",
      "quantity": 2
    },
    {
      "id": 401,
      "name": "Maceta MOD890",
      "description": "Kit de 10 macetas de barro. Compra protegida",
      "costo": "56",
      "imagen": "../Gallery/Maceta1.jpg",
      "quantity": 1
    },
    {
      "id": 402,
      "name": "Maceta MOD894",
      "description": "Kit 5 Macetas geométricas de cemento. Compra protegida",
      "costo": "500",
      "imagen": "../Gallery/Maceta2.jpg",
      "quantity": 2
    },
    {
      "id": 203,
      "name": "Herramientas NMVCG345",
      "description": "Kit de herramientas, idel para tu huerto urbano. Compra protegida",
      "costo": "123",
      "imagen": "../Gallery/Her3.jpg",
      "quantity": 1
    },
    {
      "id": 302,
      "name": "Kit Huerto Urbano BNKH7854",
      "description": "Ideal para comenzar tu huerto. Compra protegida",
      "costo": "345",
      "imagen": "../Gallery/Kit2.jpg",
      "quantity": 2
    },
    {
      "id": 304,
      "name": "Kit Huerto Urbano NBV345",
      "description": "Ideal para comenzar tu huerto. Compra protegida",
      "costo": "432",
      "imagen": "../Gallery/Kit4.jpg",
      "quantity": 1
    },
    {
      "id": 306,
      "name": "Kit Huerto Urbano BNM789",
      "description": "Ideal para comenzar tu huerto. Compra protegida",
      "costo": "456",
      "imagen": "../Gallery/Kit6.jpg",
      "quantity": 1
    },
    {
      "id": 601,
      "name": "Terrario BNH367",
      "description": "Terrario Florilandia de suculentas. Compra protegida",
      "costo": "500",
      "imagen": "../Gallery/Terrario1.jpg",
      "quantity": 1
    },
    {
      "id": 602,
      "name": "Terrario NMBb678",
      "description": "Terrario contenedor alto. Compra protegida",
      "costo": "300",
      "imagen": "../Gallery/Terrario2.jpg",
      "quantity": 1
    },
    {
      "id": 606,
      "name": "Terrario HJK3789",
      "description": "Terrario Maceta cemento. Compra protegida",
      "costo": "256",
      "imagen": "../Gallery/Terrario6.jpg",
      "quantity": 1
    },
    {
      "id": 701,
      "name": "Arreglo BNH367",
      "description": "Bonita maceta con planta. Set 2 macetas. Compra protegida",
      "costo": "300",
      "imagen": "../Gallery/Arreglo1.jpg",
      "quantity": 1
    },
    {
      "id": 702,
      "name": "Arreglo NMBb678",
      "description": "Bonita maceta con planta. Set 5 macetas. Compra protegida",
      "costo": "500",
      "imagen": "../Gallery/Arreglo2.jpg",
      "quantity": 1
    },
    {
      "id": 703,
      "name": "Arreglo GFD567",
      "description": "Bonita maceta con planta. Set 3 macetas. Compra protegida",
      "costo": "300",
      "imagen": "../Gallery/Arreglo3.jpg",
      "quantity": 1
    },
    {
      "id": 704,
      "name": "Arreglo HJK345",
      "description": "Bonita maceta con planta. Compra protegida",
      "costo": "150",
      "imagen": "../Gallery/Arreglo4.jpg",
      "quantity": 1
    },
    {
      "id": 705,
      "name": "Arreglo JKL789",
      "description": "Bonita maceta con planta. Set 2 macetas. Compra protegida",
      "costo": "300",
      "imagen": "../Gallery/Arreglo5.jpg",
      "quantity": 2
    }
  ]
}